src/__init__.py
src/file_manager.py
src/filename_processor.py
src/logseq_parser.py
src/main.py
src/obsidian_formatter.py
src/utils.py
logseq2obsidian-0.0.1.dist-info/METADATA
logseq2obsidian-0.0.1.dist-info/WHEEL
logseq2obsidian-0.0.1.dist-info/entry_points.txt
logseq2obsidian-0.0.1.dist-info/licenses/LICENSE
logseq2obsidian-0.0.1.dist-info/RECORD
