Metadata-Version: 2.4
Name: logseq2obsidian
Version: 0.0.1
Summary: A tool to convert Logseq notes to Obsidian format
License-Expression: MIT
License-File: LICENSE
Keywords: logseq,obsidian,note-taking,migration,converter
Author: Tao Zeyu
Author-email: i@taozeyu.com
Requires-Python: >=3.10
Classifier: Development Status :: 4 - Beta
Classifier: Intended Audience :: End Users/Desktop
Classifier: License :: OSI Approved :: MIT License
Classifier: Operating System :: OS Independent
Classifier: Programming Language :: Python :: 3
Classifier: Programming Language :: Python :: 3.10
Classifier: Programming Language :: Python :: 3.11
Classifier: Programming Language :: Python :: 3.12
Classifier: Topic :: Text Processing :: Markup
Classifier: Topic :: Utilities
Requires-Dist: click (>=8.1.0)
Requires-Dist: pathspec (>=0.11.0)
Project-URL: Homepage, https://github.com/moskize91/logseq2obsidian
Project-URL: Issues, https://github.com/moskize91/logseq2obsidian/issues
Project-URL: Repository, https://github.com/moskize91/logseq2obsidian
